submerger/__init__.py
submerger/merge_subtitles.py
submerger/subtitle.py
submerger/subtitle_format.py
submerger/test/__init__.py
submerger/test/execute_command.py
submerger/test/integration_test_submerger.py
submerger/test/lint_test_submerger.py
submerger/test/test_merge_subtitle.py
submerger/test/test_subtitle.py
submerger/test/test_subtitle_format.py
submerger-2023.5.13.data/scripts/submerge
submerger-2023.5.13.dist-info/LICENSE
submerger-2023.5.13.dist-info/METADATA
submerger-2023.5.13.dist-info/WHEEL
submerger-2023.5.13.dist-info/top_level.txt
submerger-2023.5.13.dist-info/RECORD
