Metadata-Version: 2.1
Name: submerger
Version: 2023.5.13
Summary: Subtitle merging tool
Home-page: https://gitlab.com/andr1i/submerger
Author: Andrii Valiukh
Author-email: andrii.valiukh0@gmail.com
Requires-Python: >=3.10
License-File: LICENSE
Provides-Extra: dev
Requires-Dist: mypy ; extra == 'dev'
Requires-Dist: pylint ; extra == 'dev'
